{
  "titanic": [
    [
      "@stree2chaava2",
      1470
    ],
    [
      "@stree2chaava2",
      1467
    ]
  ],
  "mary kom": [
    [
      "@stree2chaava2",
      1469
    ]
  ],
  "dhadak": [
    [
      "@stree2chaava2",
      1468
    ]
  ],
  "drishyam 2": [
    [
      "@stree2chaava2",
      1466
    ]
  ],
  "agilan": [
    [
      "@stree2chaava2",
      1465
    ]
  ],
  "hit 3": [
    [
      "@stree2chaava2",
      1464
    ]
  ],
  "housefull 4": [
    [
      "@stree2chaava2",
      1463
    ]
  ]
}